{"BackBroomstick":{"id": "0",
"exerciseid": "Broomstick",
"musclegroup": "Back",
"equipment": "stretch",
"exercisetype": "Stretches",
"muscleclass": "Subscapularis",
"name": "Broom Stick Subscapularis Stretch",
"preparation": "Grasp end of pole to side of head with other end of pole behind arm. Bring elbow forward slightly and bend wrist back. Reach around body with opposite arm and grasp lower end of pole. Place pole in middle of back side of upper arm. Position elbow at height of shoulder.",
"execution": "Pull lower end of pole forward so shoulder is externally rotated.. Hold stretch. Repeat with opposite arm.",
"comments": "None.",
"other": "pectoralisminor",
"target": "subscapularis"},"BackDoorway":{"id": "1",
"exerciseid": "Doorway",
"musclegroup": "Back",
"equipment": "stretch",
"exercisetype": "Stretches",
"muscleclass": "Subscapularis",
"name": "Doorway Subscapularis Stretch",
"preparation": "Stand at end of wall or in doorway facing perpendicular to wall. Bent elbow and place inside of forearm on surface of wall. Position bent elbow just below height of shoulder. Place far leg forward and near leg back.",
"execution": "Bent over at hip while bending knees slightly. Hold stretch . Repeat with opposite arm.",
"comments": "Bent knees slightly so stretch is not limited by hamstring flexibility and to keep shoulder from being pushed forward.",
"other": "pectoralisminor",
"target": "subscapularis"}}